hypersindy/__init__.py
hypersindy/dataset.py
hypersindy/equations.py
hypersindy/hypernet.py
hypersindy/hypersindy.py
hypersindy/l0.py
hypersindy/library.py
hypersindy/net.py
hypersindy/trainer.py
hypersindy/utils.py
hypersindy-0.0.4.dist-info/LICENSE.txt
hypersindy-0.0.4.dist-info/METADATA
hypersindy-0.0.4.dist-info/WHEEL
hypersindy-0.0.4.dist-info/top_level.txt
hypersindy-0.0.4.dist-info/RECORD
