Metadata-Version: 2.1
Name: hypersindy
Version: 0.0.4
Summary: HyperSINDy, a package to discover RDEs from time series data.
Author-email: Mozes Jacobs <mozesjacobs@g.harvard.edu>
Project-URL: Homepage, https://github.com/pypa/hypersindy
Project-URL: Bug Tracker, https://github.com/pypa/hypersindy/issues
Classifier: Programming Language :: Python :: 3
Classifier: License :: OSI Approved :: MIT License
Classifier: Operating System :: OS Independent
Requires-Python: >=3.7
License-File: LICENSE.txt
